rewards/__init__.py
rewards/agent.py
rewards/models.py
rewards/trainer.py
rewards/workflow.py
rewards/envs/__init__.py
rewards/envs/car.py
rewardsAI-0.0.9.dist-info/METADATA
rewardsAI-0.0.9.dist-info/WHEEL
rewardsAI-0.0.9.dist-info/top_level.txt
rewardsAI-0.0.9.dist-info/RECORD
