Metadata-Version: 2.1
Name: rewardsAI
Version: 0.0.9
Summary: Low-code RL agent training and evaluating platform.
Home-page: https://github.com/rewards-ai/rewards-sdk
Author: rewards-ai
Requires-Python: >=3.9
Requires-Dist: torch (==2.0.0)
Requires-Dist: wandb
Requires-Dist: pygame
Requires-Dist: pandas
Requires-Dist: numpy
Requires-Dist: scikit-learn
